{"v":"acercarse","en":"to approach","Indicativo":{"Presente":{"conjugated_en":"I approach, am approaching","1s":"me acerco","2s":"te acercas","3s":"se acerca","1p":"nos acercamos","2p":"os acercáis","3p":"se acercan"},"Futuro":{"conjugated_en":"I will approach","1s":"me acercaré","2s":"te acercarás","3s":"se acercará","1p":"nos acercaremos","2p":"os acercaréis","3p":"se acercarán"},"Imperfecto":{"conjugated_en":"I was approaching, used to approach, approached","1s":"me acercaba","2s":"te acercabas","3s":"se acercaba","1p":"nos acercábamos","2p":"os acercabais","3p":"se acercaban"},"Pretérito":{"conjugated_en":"I approached","1s":"me acerqué","2s":"te acercaste","3s":"se acercó","1p":"nos acercamos","2p":"acercasteis","3p":"se acercaron"},"Condicional":{"conjugated_en":"I would approach","1s":"me acercaría","2s":"te acercarías","3s":"se acercaría","1p":"nos acercaríamos","2p":"os acercaríais","3p":"se acercarían"},"Presente perfecto":{"conjugated_en":"I have approached","1s":"me he acercado","2s":"te has acercado","3s":"se ha acercado","1p":"nos hemos acercado","2p":"os habéis acercado","3p":"se han acercado"},"Futuro perfecto":{"conjugated_en":"I will have approached","1s":"me habré acercado","2s":"te habrás acercado","3s":"se habrá acercado","1p":"nos habremos acercado","2p":"os habréis acercado","3p":"se habrán acercado"},"Pluscuamperfecto":{"conjugated_en":"I had approached","1s":"me había acercado","2s":"te habías acercado","3s":"se había acercado","1p":"nos habíamos acercado","2p":"os habíais acercado","3p":"se habían acercado"},"Pretérito anterior":{"conjugated_en":"I had approached","1s":"me hube acercado","2s":"te hubiste acercado","3s":"se hubo acercado","1p":"nos hubimos acercado","2p":"os hubisteis acercado","3p":"se hubieron acercado"},"Condicional perfecto":{"conjugated_en":"I would have approached","1s":"me habría acercado","2s":"te habrías acercado","3s":"se habría acercado","1p":"nos habríamos acercado","2p":"os habríais acercado","3p":"se habrían acercado"}},"Subjuntivo":{"Presente":{"conjugated_en":"I approach, am approaching","1s":"me acerque","2s":"te acerques","3s":"se acerque","1p":"nos acerquemos","2p":"os acerquéis","3p":"se acerquen"},"Imperfecto":{"conjugated_en":"I approached, was approaching","1s":"me acercara","2s":"te acercaras","3s":"se acercara","1p":"nos acercáramos","2p":"os acercarais","3p":"se acercaran"},"Futuro":{"conjugated_en":"I will approach","1s":"me acercare","2s":"te acercares","3s":"se acercare","1p":"nos acercáremos","2p":"os acercareis","3p":"se acercaren"},"Presente perfecto":{"conjugated_en":"I have approached, approached","1s":"me haya acercado","2s":"te hayas acercado","3s":"se haya acercado","1p":"nos hayamos acercado","2p":"os hayáis acercado","3p":"se hayan acercado"},"Futuro perfecto":{"conjugated_en":"I will have approached","1s":"me hubiere acercado","2s":"te hubieres acercado","3s":"se hubiere acercado","1p":"nos hubiéremos acercado","2p":"os hubiereis acercado","3p":"se hubieren acercado"},"Pluscuamperfecto":{"conjugated_en":"I had approached","1s":"me hubiera acercado","2s":"te hubieras acercado","3s":"se hubiera acercado","1p":"nos hubiéramos acercado","2p":"os hubierais acercado","3p":"se hubieran acercado"}},"Imperativo Afirmativo":{"Presente":{"conjugated_en":"Approach! Don't approach!","1s":"","2s":"acércate","3s":"acercaos","1p":"","2p":"acérquese","3p":"acérquense"}},"Imperativo Negativo":{"Presente":{"conjugated_en":"Approach! Don't approach!","1s":"","2s":"no te acerques","3s":"no os acerquéis","1p":"","2p":"no se acerque","3p":"no se acerquen"}}}