{"v":"acordar","en":"to decide, resolve, agree [on]","gerund":"acordando","pastparticiple":"acordado","Condicional":{"Condicional":{"conjugated_en":"I would decide","1s":"acordaría","2s":"acordarías","3s":"acordaría","1p":"acordaríamos","2p":"acordaríais","3p":"acordarían"},"Condicional perfecto":{"conjugated_en":"I would have decided","1s":"habría acordado","2s":"habrías acordado","3s":"habría acordado","1p":"habríamos acordado","2p":"habríais acordado","3p":"habrían acordado"}},"Indicativo":{"Presente":{"conjugated_en":"I decide, am deciding","1s":"acuerdo","2s":"acuerdas","3s":"acuerda","1p":"acordamos","2p":"acordáis","3p":"acuerdan"},"Futuro":{"conjugated_en":"I will decide","1s":"acordaré","2s":"acordarás","3s":"acordará","1p":"acordaremos","2p":"acordaréis","3p":"acordarán"},"Imperfecto":{"conjugated_en":"I was deciding, used to decide, decided","1s":"acordaba","2s":"acordabas","3s":"acordaba","1p":"acordábamos","2p":"acordabais","3p":"acordaban"},"Pretérito":{"conjugated_en":"I decided","1s":"acordé","2s":"acordaste","3s":"acordó","1p":"acordamos","2p":"acordasteis","3p":"acordaron"},"Presente perfecto":{"conjugated_en":"I have decided","1s":"he acordado","2s":"has acordado","3s":"ha acordado","1p":"hemos acordado","2p":"habéis acordado","3p":"han acordado"},"Futuro perfecto":{"conjugated_en":"I will have decided","1s":"habré acordado","2s":"habrás acordado","3s":"habrá acordado","1p":"habremos acordado","2p":"habréis acordado","3p":"habrán acordado"},"Pluscuamperfecto":{"conjugated_en":"I had decided","1s":"había acordado","2s":"habías acordado","3s":"había acordado","1p":"habíamos acordado","2p":"habíais acordado","3p":"habían acordado"},"Pretérito anterior":{"conjugated_en":"I had decided","1s":"hube acordado","2s":"hubiste acordado","3s":"hubo acordado","1p":"hubimos acordado","2p":"hubisteis acordado","3p":"hubieron acordado"}},"Subjuntivo":{"Presente":{"conjugated_en":"I decide, am deciding","1s":"acuerde","2s":"acuerdes","3s":"acuerde","1p":"acordemos","2p":"acordéis","3p":"acuerden"},"Imperfecto":{"conjugated_en":"I decided, was deciding","1s":"acordara","2s":"acordaras","3s":"acordara","1p":"acordáramos","2p":"acordarais","3p":"acordaran"},"Futuro":{"conjugated_en":"I will decide","1s":"acordare","2s":"acordares","3s":"acordare","1p":"acordáremos","2p":"acordareis","3p":"acordaren"},"Presente perfecto":{"conjugated_en":"I have decided, decided","1s":"haya acordado","2s":"hayas acordado","3s":"haya acordado","1p":"hayamos acordado","2p":"hayáis acordado","3p":"hayan acordado"},"Futuro perfecto":{"conjugated_en":"I will have decided","1s":"hubiere acordado","2s":"hubieres acordado","3s":"hubiere acordado","1p":"hubiéremos acordado","2p":"hubiereis acordado","3p":"hubieren acordado"},"Pluscuamperfecto":{"conjugated_en":"I had decided","1s":"hubiera acordado","2s":"hubieras acordado","3s":"hubiera acordado","1p":"hubiéramos acordado","2p":"hubierais acordado","3p":"hubieran acordado"}},"Imperativo":{"Imperativo Afirmativo":{"conjugated_en":"Decide! Don't decide!","1s":"","2s":"acuerda","3s":"acordad","1p":"","2p":"acuerde","3p":"acuerden"},"Imperativo Negativo":{"conjugated_en":"Decide! Don't decide!","1s":"","2s":"no acuerdes","3s":"no acordéis","1p":"","2p":"no acuerde","3p":"no acuerden"}}}