{"v":"amar","en":"to love","Indicativo":{"Presente":{"conjugated_en":"I love, am loving","1s":"amo","2s":"amas","3s":"ama","1p":"amamos","2p":"amáis","3p":"aman"},"Futuro":{"conjugated_en":"I will love","1s":"amaré","2s":"amarás","3s":"amará","1p":"amaremos","2p":"amaréis","3p":"amarán"},"Imperfecto":{"conjugated_en":"I was loving, used to love, loved","1s":"amaba","2s":"amabas","3s":"amaba","1p":"amábamos","2p":"amabais","3p":"amaban"},"Pretérito":{"conjugated_en":"I loved","1s":"amé","2s":"amaste","3s":"amó","1p":"amamos","2p":"amasteis","3p":"amaron"},"Presente perfecto":{"conjugated_en":"I have loved","1s":"he amado","2s":"has amado","3s":"ha amado","1p":"hemos amado","2p":"habéis amado","3p":"han amado"},"Futuro perfecto":{"conjugated_en":"I will have loved","1s":"habré amado","2s":"habrás amado","3s":"habrá amado","1p":"habremos amado","2p":"habréis amado","3p":"habrán amado"},"Pluscuamperfecto":{"conjugated_en":"I had loved","1s":"había amado","2s":"habías amado","3s":"había amado","1p":"habíamos amado","2p":"habíais amado","3p":"habían amado"},"Pretérito anterior":{"conjugated_en":"I had loved","1s":"hube amado","2s":"hubiste amado","3s":"hubo amado","1p":"hubimos amado","2p":"hubisteis amado","3p":"hubieron amado"}},"Condicional":{"Condicional":{"conjugated_en":"I would love","1s":"amaría","2s":"amarías","3s":"amaría","1p":"amaríamos","2p":"amaríais","3p":"amarían"},"Condicional perfecto":{"conjugated_en":"I would have loved","1s":"habría amado","2s":"habrías amado","3s":"habría amado","1p":"habríamos amado","2p":"habríais amado","3p":"habrían amado"}},"Subjuntivo":{"Presente":{"conjugated_en":"I love, am loving","1s":"ame","2s":"ames","3s":"ame","1p":"amemos","2p":"améis","3p":"amen"},"Imperfecto":{"conjugated_en":"I loved, was loving","1s":"amara","2s":"amaras","3s":"amara","1p":"amáramos","2p":"amarais","3p":"amaran"},"Futuro":{"conjugated_en":"I will love","1s":"amare","2s":"amares","3s":"amare","1p":"amáremos","2p":"amareis","3p":"amaren"},"Presente perfecto":{"conjugated_en":"I have loved, loved","1s":"haya amado","2s":"hayas amado","3s":"haya amado","1p":"hayamos amado","2p":"hayáis amado","3p":"hayan amado"},"Futuro perfecto":{"conjugated_en":"I will have loved","1s":"hubiere amado","2s":"hubieres amado","3s":"hubiere amado","1p":"hubiéremos amado","2p":"hubiereis amado","3p":"hubieren amado"},"Pluscuamperfecto":{"conjugated_en":"I had loved","1s":"hubiera amado","2s":"hubieras amado","3s":"hubiera amado","1p":"hubiéramos amado","2p":"hubierais amado","3p":"hubieran amado"}},"Imperativo":{"Imperativo Afirmativo":{"conjugated_en":"Love! Don't love!","1s":"","2s":"ama","3s":"amad","1p":"","2p":"ame","3p":"amen"},"Imperativo Negativo":{"conjugated_en":"Love! Don't love!","1s":"","2s":"no ames","3s":"no améis","1p":"","2p":"no ame","3p":"no amen"}}}