{"v":"guardar","en":"to guard, watch over, protect, take care of; to keep, hold on to; to put away, store away","Indicativo":{"Presente":{"conjugated_en":"I guard, am guarding","1s":"guardo","2s":"guardas","3s":"guarda","1p":"guardamos","2p":"guardáis","3p":"guardan"},"Futuro":{"conjugated_en":"I will guard","1s":"guardaré","2s":"guardarás","3s":"guardará","1p":"guardaremos","2p":"guardaréis","3p":"guardarán"},"Imperfecto":{"conjugated_en":"I was guarding, used to guard, guarded","1s":"guardaba","2s":"guardabas","3s":"guardaba","1p":"guardábamos","2p":"guardabais","3p":"guardaban"},"Pretérito":{"conjugated_en":"I guarded","1s":"guardé","2s":"guardaste","3s":"guardó","1p":"guardamos","2p":"guardasteis","3p":"guardaron"},"Presente perfecto":{"conjugated_en":"I have guarded","1s":"he guardado","2s":"has guardado","3s":"ha guardado","1p":"hemos guardado","2p":"habéis guardado","3p":"han guardado"},"Futuro perfecto":{"conjugated_en":"I will have guarded","1s":"habré guardado","2s":"habrás guardado","3s":"habrá guardado","1p":"habremos guardado","2p":"habréis guardado","3p":"habrán guardado"},"Pluscuamperfecto":{"conjugated_en":"I had guarded","1s":"había guardado","2s":"habías guardado","3s":"había guardado","1p":"habíamos guardado","2p":"habíais guardado","3p":"habían guardado"},"Pretérito anterior":{"conjugated_en":"I had guarded","1s":"hube guardado","2s":"hubiste guardado","3s":"hubo guardado","1p":"hubimos guardado","2p":"hubisteis guardado","3p":"hubieron guardado"}},"Condicional":{"Condicional":{"conjugated_en":"I would guard","1s":"guardaría","2s":"guardarías","3s":"guardaría","1p":"guardaríamos","2p":"guardaríais","3p":"guardarían"},"Condicional perfecto":{"conjugated_en":"I would have guarded","1s":"habría guardado","2s":"habrías guardado","3s":"habría guardado","1p":"habríamos guardado","2p":"habríais guardado","3p":"habrían guardado"}},"Subjuntivo":{"Presente":{"conjugated_en":"I guard, am guarding","1s":"guarde","2s":"guardes","3s":"guarde","1p":"guardemos","2p":"guardéis","3p":"guarden"},"Imperfecto":{"conjugated_en":"I guarded, was guarding","1s":"guardara","2s":"guardaras","3s":"guardara","1p":"guardáramos","2p":"guardarais","3p":"guardaran"},"Futuro":{"conjugated_en":"I will guard","1s":"guardare","2s":"guardares","3s":"guardare","1p":"guardáremos","2p":"guardareis","3p":"guardaren"},"Presente perfecto":{"conjugated_en":"I have guarded, guarded","1s":"haya guardado","2s":"hayas guardado","3s":"haya guardado","1p":"hayamos guardado","2p":"hayáis guardado","3p":"hayan guardado"},"Futuro perfecto":{"conjugated_en":"I will have guarded","1s":"hubiere guardado","2s":"hubieres guardado","3s":"hubiere guardado","1p":"hubiéremos guardado","2p":"hubiereis guardado","3p":"hubieren guardado"},"Pluscuamperfecto":{"conjugated_en":"I had guarded","1s":"hubiera guardado","2s":"hubieras guardado","3s":"hubiera guardado","1p":"hubiéramos guardado","2p":"hubierais guardado","3p":"hubieran guardado"}},"Imperativo":{"Imperativo Afirmativo":{"conjugated_en":"Guard! Don't guard!","1s":"","2s":"guarda","3s":"guardad","1p":"","2p":"guarde","3p":"guarden"},"Imperativo Negativo":{"conjugated_en":"Guard! Don't guard!","1s":"","2s":"no guardes","3s":"no guardéis","1p":"","2p":"no guarde","3p":"no guarden"}}}