{"v":"hacer","en":"to do, make","gerund":"haciendo","pastparticiple":"hecho","Indicativo":{"Presente":{"conjugated_en":"I do, am doing","1s":"hago","2s":"haces","3s":"hace","1p":"hacemos","2p":"hacéis","3p":"hacen"},"Futuro":{"conjugated_en":"I will do","1s":"haré","2s":"harás","3s":"hará","1p":"haremos","2p":"haréis","3p":"harán"},"Imperfecto":{"conjugated_en":"I was doing, used to do, did","1s":"hacía","2s":"hacías","3s":"hacía","1p":"hacíamos","2p":"hacíais","3p":"hacían"},"Pretérito":{"conjugated_en":"I did","1s":"hice","2s":"hiciste","3s":"hizo","1p":"hicimos","2p":"hicisteis","3p":"hicieron"},"Presente perfecto":{"conjugated_en":"I have done","1s":"he hecho","2s":"has hecho","3s":"ha hecho","1p":"hemos hecho","2p":"habéis hecho","3p":"han hecho"},"Futuro perfecto":{"conjugated_en":"I will have done","1s":"habré hecho","2s":"habrás hecho","3s":"habrá hecho","1p":"habremos hecho","2p":"habréis hecho","3p":"habrán hecho"},"Pluscuamperfecto":{"conjugated_en":"I had done","1s":"había hecho","2s":"habías hecho","3s":"había hecho","1p":"habíamos hecho","2p":"habíais hecho","3p":"habían hecho"},"Pretérito anterior":{"conjugated_en":"I had done","1s":"hube hecho","2s":"hubiste hecho","3s":"hubo hecho","1p":"hubimos hecho","2p":"hubisteis hecho","3p":"hubieron hecho"}},"Condicional":{"Condicional":{"conjugated_en":"I would do","1s":"haría","2s":"harías","3s":"haría","1p":"haríamos","2p":"haríais","3p":"harían"},"Condicional perfecto":{"conjugated_en":"I would have done","1s":"habría hecho","2s":"habrías hecho","3s":"habría hecho","1p":"habríamos hecho","2p":"habríais hecho","3p":"habrían hecho"}},"Subjuntivo":{"Presente":{"conjugated_en":"I do, am doing","1s":"haga","2s":"hagas","3s":"haga","1p":"hagamos","2p":"hagáis","3p":"hagan"},"Imperfecto":{"conjugated_en":"I did, was doing","1s":"hiciera","2s":"hicieras","3s":"hiciera","1p":"hiciéramos","2p":"hicierais","3p":"hicieran"},"Futuro":{"conjugated_en":"I will do","1s":"hiciere","2s":"hicieres","3s":"hiciere","1p":"hiciéremos","2p":"hiciereis","3p":"hicieren"},"Presente perfecto":{"conjugated_en":"I have done, did","1s":"haya hecho","2s":"hayas hecho","3s":"haya hecho","1p":"hayamos hecho","2p":"hayáis hecho","3p":"hayan hecho"},"Futuro perfecto":{"conjugated_en":"I will have done","1s":"hubiere hecho","2s":"hubieres hecho","3s":"hubiere hecho","1p":"hubiéremos hecho","2p":"hubiereis hecho","3p":"hubieren hecho"},"Pluscuamperfecto":{"conjugated_en":"I had done","1s":"hubiera hecho","2s":"hubieras hecho","3s":"hubiera hecho","1p":"hubiéramos hecho","2p":"hubierais hecho","3p":"hubieran hecho"}},"Imperativo":{"Imperativo Afirmativo":{"conjugated_en":"Do! Don't do!","1s":"","2s":"haz","3s":"haced","1p":"","2p":"haga","3p":"hagan"},"Imperativo Negativo":{"conjugated_en":"Do! Don't do!","1s":"","2s":"no hagas","3s":"no hagáis","1p":"","2p":"no haga","3p":"no hagan"}}}