{"v":"invadir","en":"to invade, overrun","Indicativo":{"Presente":{"conjugated_en":"I invade, am invading","1s":"invado","2s":"invades","3s":"invade","1p":"invadimos","2p":"invadís","3p":"invaden"},"Futuro":{"conjugated_en":"I will invade","1s":"invadiré","2s":"invadirás","3s":"invadirá","1p":"invadiremos","2p":"invadiréis","3p":"invadirán"},"Imperfecto":{"conjugated_en":"I was invading, used to invade, invaded","1s":"invadía","2s":"invadías","3s":"invadía","1p":"invadíamos","2p":"invadíais","3p":"invadían"},"Pretérito":{"conjugated_en":"I invaded","1s":"invadí","2s":"invadiste","3s":"invadió","1p":"invadimos","2p":"invadisteis","3p":"invadieron"},"Condicional":{"conjugated_en":"I would invade","1s":"invadiría","2s":"invadirías","3s":"invadiría","1p":"invadiríamos","2p":"invadiríais","3p":"invadirían"},"Presente perfecto":{"conjugated_en":"I have invaded","1s":"he invadido","2s":"has invadido","3s":"ha invadido","1p":"hemos invadido","2p":"habéis invadido","3p":"han invadido"},"Futuro perfecto":{"conjugated_en":"I will have invaded","1s":"habré invadido","2s":"habrás invadido","3s":"habrá invadido","1p":"habremos invadido","2p":"habréis invadido","3p":"habrán invadido"},"Pluscuamperfecto":{"conjugated_en":"I had invaded","1s":"había invadido","2s":"habías invadido","3s":"había invadido","1p":"habíamos invadido","2p":"habíais invadido","3p":"habían invadido"},"Pretérito anterior":{"conjugated_en":"I had invaded","1s":"hube invadido","2s":"hubiste invadido","3s":"hubo invadido","1p":"hubimos invadido","2p":"hubisteis invadido","3p":"hubieron invadido"},"Condicional perfecto":{"conjugated_en":"I would have invaded","1s":"habría invadido","2s":"habrías invadido","3s":"habría invadido","1p":"habríamos invadido","2p":"habríais invadido","3p":"habrían invadido"}},"Subjuntivo":{"Presente":{"conjugated_en":"I invade, am invading","1s":"invada","2s":"invadas","3s":"invada","1p":"invadamos","2p":"invadáis","3p":"invadan"},"Imperfecto":{"conjugated_en":"I invaded, was invading","1s":"invadiera","2s":"invadieras","3s":"invadiera","1p":"invadiéramos","2p":"invadierais","3p":"invadieran"},"Futuro":{"conjugated_en":"I will invade","1s":"invadiere","2s":"invadieres","3s":"invadiere","1p":"invadiéremos","2p":"invadiereis","3p":"invadieren"},"Presente perfecto":{"conjugated_en":"I have invaded, invaded","1s":"haya invadido","2s":"hayas invadido","3s":"haya invadido","1p":"hayamos invadido","2p":"hayáis invadido","3p":"hayan invadido"},"Futuro perfecto":{"conjugated_en":"I will have invaded","1s":"hubiere invadido","2s":"hubieres invadido","3s":"hubiere invadido","1p":"hubiéremos invadido","2p":"hubiereis invadido","3p":"hubieren invadido"},"Pluscuamperfecto":{"conjugated_en":"I had invaded","1s":"hubiera invadido","2s":"hubieras invadido","3s":"hubiera invadido","1p":"hubiéramos invadido","2p":"hubierais invadido","3p":"hubieran invadido"}},"Imperativo Afirmativo":{"Presente":{"conjugated_en":"Invade! Don't invade!","1s":"","2s":"invade","3s":"invadid","1p":"","2p":"invada","3p":"invadan"}},"Imperativo Negativo":{"Presente":{"conjugated_en":"Invade! Don't invade!","1s":"","2s":"no invadas","3s":"no invadáis","1p":"","2p":"no invada","3p":"no invadan"}}}