{"v":"mostrar","en":"to show","Indicativo":{"Presente":{"conjugated_en":"I show, am showing","1s":"muestro","2s":"muestras","3s":"muestra","1p":"mostramos","2p":"mostráis","3p":"muestran"},"Futuro":{"conjugated_en":"I will show","1s":"mostraré","2s":"mostrarás","3s":"mostrará","1p":"mostraremos","2p":"mostraréis","3p":"mostrarán"},"Imperfecto":{"conjugated_en":"I was showing, used to show, showed","1s":"mostraba","2s":"mostrabas","3s":"mostraba","1p":"mostrábamos","2p":"mostrabais","3p":"mostraban"},"Pretérito":{"conjugated_en":"I showed","1s":"mostré","2s":"mostraste","3s":"mostró","1p":"mostramos","2p":"mostrasteis","3p":"mostraron"},"Presente perfecto":{"conjugated_en":"I have shown","1s":"he mostrado","2s":"has mostrado","3s":"ha mostrado","1p":"hemos mostrado","2p":"habéis mostrado","3p":"han mostrado"},"Futuro perfecto":{"conjugated_en":"I will have shown","1s":"habré mostrado","2s":"habrás mostrado","3s":"habrá mostrado","1p":"habremos mostrado","2p":"habréis mostrado","3p":"habrán mostrado"},"Pluscuamperfecto":{"conjugated_en":"I had shown","1s":"había mostrado","2s":"habías mostrado","3s":"había mostrado","1p":"habíamos mostrado","2p":"habíais mostrado","3p":"habían mostrado"},"Pretérito anterior":{"conjugated_en":"I had shown","1s":"hube mostrado","2s":"hubiste mostrado","3s":"hubo mostrado","1p":"hubimos mostrado","2p":"hubisteis mostrado","3p":"hubieron mostrado"}},"Condicional":{"Condicional":{"conjugated_en":"I would show","1s":"mostraría","2s":"mostrarías","3s":"mostraría","1p":"mostraríamos","2p":"mostraríais","3p":"mostrarían"},"Condicional perfecto":{"conjugated_en":"I would have shown","1s":"habría mostrado","2s":"habrías mostrado","3s":"habría mostrado","1p":"habríamos mostrado","2p":"habríais mostrado","3p":"habrían mostrado"}},"Subjuntivo":{"Presente":{"conjugated_en":"I show, am showing","1s":"muestre","2s":"muestres","3s":"muestre","1p":"mostremos","2p":"mostréis","3p":"muestren"},"Imperfecto":{"conjugated_en":"I showed, was showing","1s":"mostrara","2s":"mostraras","3s":"mostrara","1p":"mostráramos","2p":"mostrarais","3p":"mostraran"},"Futuro":{"conjugated_en":"I will show","1s":"mostrare","2s":"mostrares","3s":"mostrare","1p":"mostráremos","2p":"mostrareis","3p":"mostraren"},"Presente perfecto":{"conjugated_en":"I have shown, showed","1s":"haya mostrado","2s":"hayas mostrado","3s":"haya mostrado","1p":"hayamos mostrado","2p":"hayáis mostrado","3p":"hayan mostrado"},"Futuro perfecto":{"conjugated_en":"I will have shown","1s":"hubiere mostrado","2s":"hubieres mostrado","3s":"hubiere mostrado","1p":"hubiéremos mostrado","2p":"hubiereis mostrado","3p":"hubieren mostrado"},"Pluscuamperfecto":{"conjugated_en":"I had shown","1s":"hubiera mostrado","2s":"hubieras mostrado","3s":"hubiera mostrado","1p":"hubiéramos mostrado","2p":"hubierais mostrado","3p":"hubieran mostrado"}},"Imperativo":{"Imperativo Afirmativo":{"conjugated_en":"Show! Don't show!","1s":"","2s":"muestra","3s":"mostrad","1p":"","2p":"muestre","3p":"muestren"},"Imperativo Negativo":{"conjugated_en":"Show! Don't show!","1s":"","2s":"no muestres","3s":"no mostréis","1p":"","2p":"no muestre","3p":"no muestren"}}}