{"v":"variar","en":"to vary","Indicativo":{"Presente":{"conjugated_en":"I vary, am varying","1s":"varío","2s":"varías","3s":"varía","1p":"variamos","2p":"variáis","3p":"varían"},"Futuro":{"conjugated_en":"I will vary","1s":"variaré","2s":"variarás","3s":"variará","1p":"variaremos","2p":"variaréis","3p":"variarán"},"Imperfecto":{"conjugated_en":"I was varying, used to vary, varied","1s":"variaba","2s":"variabas","3s":"variaba","1p":"variábamos","2p":"variabais","3p":"variaban"},"Pretérito":{"conjugated_en":"I varied","1s":"varié","2s":"variaste","3s":"varió","1p":"variamos","2p":"variasteis","3p":"variaron"},"Presente perfecto":{"conjugated_en":"I have varied","1s":"he variado","2s":"has variado","3s":"ha variado","1p":"hemos variado","2p":"habéis variado","3p":"han variado"},"Futuro perfecto":{"conjugated_en":"I will have varied","1s":"habré variado","2s":"habrás variado","3s":"habrá variado","1p":"habremos variado","2p":"habréis variado","3p":"habrán variado"},"Pluscuamperfecto":{"conjugated_en":"I had varied","1s":"había variado","2s":"habías variado","3s":"había variado","1p":"habíamos variado","2p":"habíais variado","3p":"habían variado"},"Pretérito anterior":{"conjugated_en":"I had varied","1s":"hube variado","2s":"hubiste variado","3s":"hubo variado","1p":"hubimos variado","2p":"hubisteis variado","3p":"hubieron variado"}},"Condicional":{"Condicional":{"conjugated_en":"I would vary","1s":"variaría","2s":"variarías","3s":"variaría","1p":"variaríamos","2p":"variaríais","3p":"variarían"},"Condicional perfecto":{"conjugated_en":"I would have varied","1s":"habría variado","2s":"habrías variado","3s":"habría variado","1p":"habríamos variado","2p":"habríais variado","3p":"habrían variado"}},"Subjuntivo":{"Presente":{"conjugated_en":"I vary, am varying","1s":"varíe","2s":"varíes","3s":"varíe","1p":"variemos","2p":"variéis","3p":"varíen"},"Imperfecto":{"conjugated_en":"I varied, was varying","1s":"variara","2s":"variaras","3s":"variara","1p":"variáramos","2p":"variarais","3p":"variaran"},"Futuro":{"conjugated_en":"I will vary","1s":"variare","2s":"variares","3s":"variare","1p":"variáremos","2p":"variareis","3p":"variaren"},"Presente perfecto":{"conjugated_en":"I have varied, varied","1s":"haya variado","2s":"hayas variado","3s":"haya variado","1p":"hayamos variado","2p":"hayáis variado","3p":"hayan variado"},"Futuro perfecto":{"conjugated_en":"I will have varied","1s":"hubiere variado","2s":"hubieres variado","3s":"hubiere variado","1p":"hubiéremos variado","2p":"hubiereis variado","3p":"hubieren variado"},"Pluscuamperfecto":{"conjugated_en":"I had varied","1s":"hubiera variado","2s":"hubieras variado","3s":"hubiera variado","1p":"hubiéramos variado","2p":"hubierais variado","3p":"hubieran variado"}},"Imperativo":{"Imperativo Afirmativo":{"conjugated_en":"Vary! Don't vary!","1s":"","2s":"varía","3s":"variad","1p":"","2p":"varíe","3p":"varíen"},"Imperativo Negativo":{"conjugated_en":"Vary! Don't vary!","1s":"","2s":"no varíes","3s":"no variéis","1p":"","2p":"no varíe","3p":"no varíen"}}}